{
    "version": "https://jsonfeed.org/version/1",
    "title": "全球实时新闻资讯",
    "home_page_url": "https://loear.github.io/news/",
    "feed_url": "https://loear.github.io/news/rss.json",
    "description": "全球实时新闻资讯",
    "items": [
        {
            "id": 3641109,
            "content_html": "",
            "url": "https://finance.sina.cn/7x24/2024-06-01/detail-inaxfzrs2582318.d.html",
            "title": "【新劲刚：电磁波吸收材料已实现小批量产】新劲刚在互动平台表示，公司在电磁屏蔽材料领域拥有自己的核心技术及相关发明专利，电磁波吸收材料产品可有效吸收、衰减电磁波能量，同时具备轻质、宽频、高效、高强、高韧等特点，可有效提高应用于特殊领域的设施的突击及生存能力，可广泛应用于飞行器、舰船、车辆及地面、电子等特殊领域。目前已实现小批量产，结构吸波功能材料制品已通过客户的前期产技术验证。",
            "date_modified": "2024-06-01T14:19:47.000Z"
        },
        {
            "id": 3641108,
            "content_html": "",
            "url": "https://finance.sina.cn/7x24/2024-06-01/detail-inaxhcth7852136.d.html",
            "title": "【安徽芜湖再通报黄金回收店“鬼秤”事件：拟对涉事店铺罚款并列入严重违法失信名单】6月1日，针对“网络博主打假称安徽芜湖一金店惊现‘五两秤’”一事，安徽芜湖市镜湖区市场监督管理局再度发布情况通报。通报称，经查明，该店使用加装芯片改造破坏其准确度的计量器具从事贵金属回收贸易结算；在收购贵金属经营活动中未保证商品量的量值准确。镜湖区市场监督管理局表示，5月29日，该局依法向当事人送达行政处罚告知书、拟列入严重违法失信名单告知书，根据《中华人民共和国计量法》《商品量计量违法行为处罚规定》，拟合并顶格处以罚款22000元；拟将该店列入严重违法失信名单，并实施相应管理措施。",
            "date_modified": "2024-06-01T14:15:38.000Z"
        },
        {
            "id": 3641106,
            "content_html": "",
            "url": "https://finance.sina.cn/7x24/2024-06-01/detail-inaxhctk4628853.d.html",
            "title": "【杰哈德称将根据自身要求评估加沙停火协议草案】当地时间6月1日，针对31日美国总统拜登发表讲话呼吁巴勒斯坦伊斯兰抵抗运动（哈马斯）接受以色列提出的新的被扣押人员交换方案和停火协议草案，巴勒斯坦伊斯兰圣战组织（杰哈德）发表声明称，虽然美方似乎改变了立场，但杰哈德对其仍持怀疑态度，因为美方对以色列的偏袒依然是明确和公开的，美方仍通过持续向以色列提供武器及对抗谴责以色列的国际机构等方式掩盖以色列对加沙民众的侵犯。（央视新闻）",
            "date_modified": "2024-06-01T14:11:23.000Z"
        },
        {
            "id": 3641105,
            "content_html": "",
            "url": "https://finance.sina.cn/7x24/2024-06-01/detail-inaxhctk4628718.d.html",
            "title": "【萨尔瓦多当选总统布克尔宣誓就职】当地时间6月1日，萨尔瓦多当选总统布克尔在首都圣萨尔瓦多宣誓就职。在当天举行的宣誓就职仪式上，萨尔瓦多国民议会议长卡斯特罗为布克尔戴上总统绶带，布克尔随后宣誓就任萨尔瓦多总统。（央视新闻）",
            "date_modified": "2024-06-01T14:10:20.000Z"
        },
        {
            "id": 3641104,
            "content_html": "",
            "url": "https://finance.sina.cn/7x24/2024-06-01/detail-inaxfzrt9355527.d.html",
            "title": "【山东宁阳一煤矿发生透水事故致8人被困】记者1日从山东省泰安市宁阳县相关部门获悉，位于宁阳县的山东能源华丰煤矿发生透水事故，导致8人被困，目前救援工作仍在进行中。（新华社）",
            "date_modified": "2024-06-01T14:01:48.000Z"
        },
        {
            "id": 3641103,
            "content_html": "",
            "url": "https://finance.sina.cn/7x24/2024-06-01/detail-inaxhctk4627731.d.html",
            "title": "【航行警告 渤海部分海域军事试验】据中国海事局网站消息，秦皇岛海事局发布航行警告，6月2日至3日每日7时至21时，渤海部分海域执行军事科研试验，禁止驶入。",
            "date_modified": "2024-06-01T14:00:36.000Z"
        },
        {
            "id": 3641102,
            "content_html": "",
            "url": "https://finance.sina.cn/7x24/2024-06-01/detail-inaxfzrt9354833.d.html",
            "title": "【广合科技：配合客户进行AI PC产品的样品制作】广合科技在互动平台表示，公司有配合客户进行AI PC产品的样品制作。",
            "date_modified": "2024-06-01T13:58:50.000Z"
        },
        {
            "id": 3641101,
            "content_html": "",
            "url": "https://finance.sina.cn/7x24/2024-06-01/detail-inaxfzrt9354548.d.html",
            "title": "印度5月征收1.73万亿卢比（1501.3亿元）的商品和服务税。",
            "date_modified": "2024-06-01T13:56:51.000Z"
        },
        {
            "id": 3641100,
            "content_html": "",
            "url": "https://finance.sina.cn/7x24/2024-06-01/detail-inaxfzrs2577650.d.html",
            "title": "【苏丹西部法希尔市冲突持续 至少10人死亡】苏丹快速支援部队于5月31日在苏丹西部北达尔富尔州首府法希尔市南部至少五个社区展开袭击，造成至少10人死亡。此外，法希尔市南部医院的外墙也遭到炮击，但并未造成人员伤亡。目前，法希尔市全部三家主要医院——南部医院、儿童医院与妇产医院都在战火中不同程度受损，只剩两家医院仍在勉强运行。自5月10日起，苏丹快速支援部队开始围攻法希尔市，苏丹武装部队联合当地结盟的地方武装展开反击。近期，法希尔市的局势不断恶化。（央视新闻）",
            "date_modified": "2024-06-01T13:56:39.000Z"
        },
        {
            "id": 3641099,
            "content_html": "",
            "url": "https://finance.sina.cn/7x24/2024-06-01/detail-inaxhcth7850231.d.html",
            "title": "消息人士称，一些欧佩克+部长前往利雅得参加石油产量会议。",
            "date_modified": "2024-06-01T13:56:31.000Z"
        },
        {
            "id": 3641098,
            "content_html": "",
            "url": "https://finance.sina.cn/7x24/2024-06-01/detail-inaxfzrt9354312.d.html",
            "title": "【台风残留云系带来降雨 海南、广东、福建部分中小河流可能超警】据水利部消息，今年第2号台风“马力斯”今天在广东省登陆后，强度逐渐减弱，已于17时停止编号。受其影响，海南文昌市文教河、福建闽江上游建溪支流松溪等2条中小河流发生小幅超警洪水，目前水位仍在上涨。据预测，受残留云系影响，今晚到明天，华南东部、江南东南部等地将有大到暴雨，其中广东、福建、浙江等省部分地区将有大暴雨。海南、广东沿海、福建闽江上游建溪部分支流等暴雨区内中小河流可能发生超警以上洪水。水利部要求密切监视雨水情变化，重点做好强降雨区内中小河流洪水和山洪灾害防御，中小型水库、病险水库、在建水利工程安全度汛工作。广东省、福建省、浙江省水利厅分别启动防汛Ⅳ级应急响应。",
            "date_modified": "2024-06-01T13:55:28.000Z"
        },
        {
            "id": 3641097,
            "content_html": "",
            "url": "https://finance.sina.cn/7x24/2024-06-01/detail-inaxfzrs2576507.d.html",
            "title": "【方大航空国际总部在渝揭牌 航空城项目启动建设】5月31日，方大航空国际总部在渝揭牌，这标志着重庆市人民政府与辽宁方大集团共同打造的方大重庆航空城项目进入启动建设阶段。辽宁方大集团是一家以碳素、钢铁、医药、商业、航空五大板块为核心的大型企业集团。今年4月，该集团与重庆市人民政府签署战略合作协议。根据协议，双方将深化在临空产业、物流服务、医疗康养等领域战略合作。（新京报）",
            "date_modified": "2024-06-01T13:50:05.000Z"
        },
        {
            "id": 3641096,
            "content_html": "",
            "url": "https://finance.sina.cn/7x24/2024-06-01/detail-inaxfzrt9352713.d.html",
            "title": "【南非大选初步统计结果揭晓】根据南非独立选举委员会对超过99%选票的统计结果，非国大获得40.25%的选票；最大反对党民主联盟获得21.70%的选票，位列第二；排名第三的是新成立的“民族之矛党”，得票率为14.68%。分析人士表示，鉴于非国大得票率未达到50%，没有获得多数席位，该党将寻求与其他政党联合，以确保继续执政。（新华网）",
            "date_modified": "2024-06-01T13:46:32.000Z"
        },
        {
            "id": 3641095,
            "content_html": "",
            "url": "https://finance.sina.cn/7x24/2024-06-01/detail-inaxfzrs2575796.d.html",
            "title": "【阿维塔5月交付4569台，同比增长163%】6月1日，阿维塔宣布，2024年5月份共交付4569台，同比增长163%。",
            "date_modified": "2024-06-01T13:46:15.000Z"
        },
        {
            "id": 3641094,
            "content_html": "",
            "url": "https://finance.sina.cn/7x24/2024-06-01/detail-inaxhctk4626046.d.html",
            "title": "【澜起科技：AI芯片在手订单金额合计已超过9000万元】澜起科技在互动平台表示，受益于AI产业趋势对相关产品需求的推动，截至2024年4月22日，公司预计在2024年第二季度交付的PCIe Retimer、MRCD/MDB及CKD芯片的在手订单金额合计已超过9000万元，上述三款AI高性能“运力”芯片呈现良好成长态势。",
            "date_modified": "2024-06-01T13:42:04.000Z"
        },
        {
            "id": 3641093,
            "content_html": "",
            "url": "https://finance.sina.cn/7x24/2024-06-01/detail-inaxfzrs2574429.d.html",
            "title": "【帝尔激光：TGV激光微孔设备已实现小批量订单】帝尔激光在互动平台表示，公司的TGV激光微孔设备已经实现小批量订单，公司将继续提升TGV激光通孔设备的性能指标，积极推进相关技术迭代升级以响应更高的产业需求。",
            "date_modified": "2024-06-01T13:39:30.000Z"
        },
        {
            "id": 3641092,
            "content_html": "",
            "url": "https://finance.sina.cn/7x24/2024-06-01/detail-inaxfzrs2573788.d.html",
            "title": "【空气动力与未来飞行科普实验室揭牌】 据中国航天科技集团消息，5月30日，空气动力与未来飞行科普实验室（简称科普实验室）在中国科学技术馆正式揭牌。科普实验室将搭建高新技术数字化科普仿真平台，展示未来新概念飞行器设计、空气动力数值模拟与性能评估、流场动态等。",
            "date_modified": "2024-06-01T13:36:12.000Z"
        },
        {
            "id": 3641091,
            "content_html": "",
            "url": "https://finance.sina.cn/7x24/2024-06-01/detail-inaxfzrt9350353.d.html",
            "title": "市场消息：南非颁布法律允许提前提取退休金。",
            "date_modified": "2024-06-01T13:35:07.000Z"
        },
        {
            "id": 3641090,
            "content_html": "",
            "url": "https://finance.sina.cn/7x24/2024-06-01/detail-inaxfzrt9349277.d.html",
            "title": "【朝鲜发文谴责美侦察机飞临朝鲜半岛】朝中社5月31日发表文章，对美国侦察机飞临朝鲜半岛表示强烈谴责，并警告称肆意妄动只会招致不可预测的灾难性后果。文章指出，美国空军RC-135U侦察机5月29日从日本起飞，逼近朝鲜南侧。此外，美军还出动多种侦察机，几乎全天候对朝鲜进行监视侦察活动。（央视军事）",
            "date_modified": "2024-06-01T13:30:51.000Z"
        },
        {
            "id": 3641089,
            "content_html": "",
            "url": "https://finance.sina.cn/7x24/2024-06-01/detail-inaxfzrt9348979.d.html",
            "title": "【一汽红旗5月零售销量达30800辆，同比增长33.8%】6月1日，一汽红旗宣布，红旗品牌5月零售销量突破30,800辆，同比增长33.8%；1-5月零售销量达156,800辆，同比增长26.3%。",
            "date_modified": "2024-06-01T13:29:16.000Z"
        },
        {
            "id": 3641088,
            "content_html": "",
            "url": "https://finance.sina.cn/7x24/2024-06-01/detail-inaxfzrs2571766.d.html",
            "title": "【暑期房车预订已提前开启：房车订单量同比增长60%】据房车生活家披露的数据显示，随着暑期的临近，房车的预订已经提前开始。截至5月底，房车生活家暑期订单量较去年同期增长超60%，平均预定时长超过15天。截至目前，从今年暑期的预订来看，新疆地区的房车预订同比增长25%左右。往年西北地区的房车预订，新疆地区的占比一般在六成，今年暑期活有望达七八成。（澎湃新闻）",
            "date_modified": "2024-06-01T13:27:49.000Z"
        },
        {
            "id": 3641087,
            "content_html": "",
            "url": "https://finance.sina.cn/7x24/2024-06-01/detail-inaxfzrs2571588.d.html",
            "title": "【2026年中国人形机器人产业规模或破200亿元】人形机器人是未来感十足的一个代表产业，有机构报告显示，预计到2026年中国人形机器人产业规模将突破200亿元。在生成式人工智能技术大爆发的当下，未来人形机器人更是极有可能实现超预期增长。（央视财经）",
            "date_modified": "2024-06-01T13:27:01.000Z"
        },
        {
            "id": 3641086,
            "content_html": "",
            "url": "https://finance.sina.cn/7x24/2024-06-01/detail-inaxfzrs2571066.d.html",
            "title": "法国总统马克龙：支持拜登关于加沙停火的提议。",
            "date_modified": "2024-06-01T13:24:42.000Z"
        },
        {
            "id": 3641084,
            "content_html": "",
            "url": "https://finance.sina.cn/7x24/2024-06-01/detail-inaxfviu2700377.d.html",
            "title": "【华勤技术将被纳入沪深300指数】 5月31日，中证指数有限公司发布公告称，将调整沪深300、中证500、中证1000、上证50、上证180、上证380和科创50等指数样本，此次调整为指数样本的定期例行调整，定期调整方案将于6月14日收市后正式生效。其中，华勤技术将被纳入沪深300指数。",
            "date_modified": "2024-06-01T13:17:22.000Z"
        },
        {
            "id": 3641083,
            "content_html": "",
            "title": "【阿拉伯国家联盟秘书长访问上海】6月1日，上海市委常委、副市长华源在市政府会见了阿拉伯国家联盟秘书长艾哈迈德·阿布·盖特一行，宾主双方就加强中阿改革发展研究中心建设等交换了意见。 (上观)",
            "date_modified": "2024-06-01T13:16:52.000Z"
        },
        {
            "id": 3641082,
            "content_html": "",
            "url": "https://finance.sina.cn/7x24/2024-06-01/detail-inaxfviu2700286.d.html",
            "title": "【俄货运飞船与国际空间站对接】俄罗斯国家航天集团6月1日在官网发布消息说，俄“进步MS-27”货运飞船当天已与国际空间站完成对接。 消息说，莫斯科时间6月1日14时43分（北京时间19时43分），“进步MS-27”货运飞船与国际空间站俄罗斯舱段的“搜索”号模块完成自动对接。5月30日，“进步MS-27”货运飞船由“联盟-2.1a”运载火箭从哈萨克斯坦境内的拜科努尔航天发射场升空，为国际空间站送货。据介绍，飞船向国际空间站运送了2504千克货物，包括燃料、饮用水、食物、氮气和各类设备等。（新华社）",
            "date_modified": "2024-06-01T13:16:48.000Z"
        },
        {
            "id": 3641080,
            "content_html": "",
            "url": "https://finance.sina.cn/7x24/2024-06-01/detail-inaxfxmk7975999.d.html",
            "title": "民调显示，印度总理莫迪的人民党联盟预计将在大选中赢得多数席位。",
            "date_modified": "2024-06-01T13:08:37.000Z"
        },
        {
            "id": 3641079,
            "content_html": "",
            "url": "https://finance.sina.cn/7x24/2024-06-01/detail-inaxfviu2697298.d.html",
            "title": "【广东江门川山群岛客运航线计划明日复航】从广东江门海事局了解到，随着台风天气影响减弱，江门海事局于6月1日20时30分停止防台风Ⅳ级应急响应。广东江门川山群岛高速客船、车渡船航线计划于6月2日8时15分起有序恢复营运与服务。",
            "date_modified": "2024-06-01T13:04:19.000Z"
        },
        {
            "id": 3641078,
            "content_html": "",
            "url": "https://finance.sina.cn/7x24/2024-06-01/detail-inaxfviu2695973.d.html",
            "title": "【南航恢复加德满都-广州往返航班】中国南方航空公司6月1日恢复加德满都-广州往返航班。 搭载73名乘客的南航CZ6067航班当天下午从广州飞抵加德满都。尼泊尔文化、旅游和民航部部长塔芒在加德满都特里布万国际机场举行的欢迎仪式上表示，希望看到南航航班持续往返加德满都，尼泊尔政府和人民永远欢迎来自中国的游客和航班。 中国驻尼泊尔大使馆参赞谢宇表示，希望南航航班为中尼经贸和旅游合作作出积极贡献。（新华社）",
            "date_modified": "2024-06-01T12:59:49.000Z"
        },
        {
            "id": 3641077,
            "content_html": "",
            "url": "https://finance.sina.cn/7x24/2024-06-01/detail-inaxfxmn4751282.d.html",
            "title": "【中国女排3比0泰国女排】2024年世界女排联赛第二周中国澳门站，中国女排vs泰国女排，最终中国女排以3:0战胜泰国女排。",
            "date_modified": "2024-06-01T12:53:34.000Z"
        },
        {
            "id": 3641076,
            "content_html": "",
            "url": "https://finance.sina.cn/7x24/2024-06-01/detail-inaxfviv9471397.d.html",
            "title": "【时代新材与大唐集团开展风电叶片技术交流】据时代新材消息，5月29日，来自中国大唐集团旗下11家二级单位（涉及京津冀、湖南、福建等13个省市区）的15位技术专家来到时代新材风电产品事业部，开展风电叶片后市场运维专项技术交流。围绕业主单位面临的重点叶片售后问题和业务需求，与会人员共同研讨风电叶片售后问题的解决方案，探索业主单位与叶片厂商售后业务合作新模式。",
            "date_modified": "2024-06-01T12:53:12.000Z"
        },
        {
            "id": 3641075,
            "content_html": "",
            "title": "【埃及专家：阿中合作树立了南南合作的典范】5月30日，中阿合作论坛第十届部长级会议在京成功举行，取得丰硕成果。中国问题专家、埃及贝尼苏韦夫大学政治学教授纳迪娅·希勒米（Nadia Helmy）在接受记者专访时指出，此次会议是首届中国－阿拉伯国家峰会后中阿合作论坛举办的首次部长会，具有承前启后的重要意义，阿拉伯国家和中国在许多领域达成共识，将为阿中关系注入更多新动力。（国际在线）",
            "date_modified": "2024-06-01T12:51:23.000Z"
        },
        {
            "id": 3641074,
            "content_html": "",
            "url": "https://finance.sina.cn/7x24/2024-06-01/detail-inaxfviu2693641.d.html",
            "title": "【无人机已改变地面战争作战样式】提及现代战争中无人机的应用，军事科学院战争研究院研究员曹延中表示，目前传统陆军的主要作战力量面临着无人机的威胁，无人机已改变地面战争的作战样式。国防科技大学国防科技战略研究智库研究员朱启超则表示，各国对于无人机的运用热情很高，但是还没有形成国际公认的安全运用规则。（CGTN）",
            "date_modified": "2024-06-01T12:49:11.000Z"
        },
        {
            "id": 3641073,
            "content_html": "",
            "url": "https://finance.sina.cn/7x24/2024-06-01/detail-inaxfxmk7973617.d.html",
            "title": "西班牙检察官表示，西班牙对外银行将面临间谍调查的审判。",
            "date_modified": "2024-06-01T12:48:52.000Z"
        },
        {
            "id": 3641072,
            "content_html": "",
            "url": "https://finance.sina.cn/7x24/2024-06-01/detail-inaxfviu2693028.d.html",
            "title": "【长三角种业创新实验室联盟在南京成立】长三角种业创新实验室联盟6月1日在南京成立。据介绍，这是首个由长三角地区相关实验室联合组建的专业领域联盟，标志着江苏省实验室联盟体系建设取得新进展。该实验室联盟由南京农业大学作物遗传与种质创新利用全国重点实验室牵头，成员单位28家，包括生物育种钟山实验室（江苏）、中国科学院植物性状形成与塑造重点实验室（上海）、水稻生物育种全国重点实验室（浙江）、省部共建茶树生物学与资源利用国家重点实验室（安徽）等来自长三角三省一市的全国（国家）重点实验室、省实验室及省部级重点实验室，联盟将围绕打造长三角科技创新共同体的总目标，聚焦种业领域关键核心技术，积极衔接国家战略任务及产业重大需求，着力构建种业领域实验室跨区域、跨学科、大协作和产学研用协同创新机制，助力长三角地区乃至全国种业科技的高质量发展。江苏省已按照“1+N”的模式成立了江苏省实验室联盟和高端装备、通信2个专业领域联盟，长三角种业创新实验室联盟是成立的第3个领域联盟。（央视新闻）",
            "date_modified": "2024-06-01T12:46:59.000Z"
        },
        {
            "id": 3641071,
            "content_html": "",
            "url": "https://finance.sina.cn/7x24/2024-06-01/detail-inaxfviv9469796.d.html",
            "title": "【外媒：联合国伊拉克援助团2025年底撤离】据法新社5月31日报道，应伊拉克要求，联合国安理会31日同意在2025年底让进驻当地超过20年的联合国伊拉克援助团（联伊援助团）撤离伊拉克。 报道称，伊拉克政府对这一决定表示赞赏，称决定“反映了”2003年以来“伊拉克取得的重大进展”，尤其是在经济发展和“良好治理”方面。伊拉克政府5月初要求联伊援助团在2025年12月31日撤离。 伊拉克政府发言人在一份公报中保证说，伊拉克政府仍致力于“继续与联合国及其发展计划合作并建立持久伙伴关系”。 报道称，联合国安理会通过的决议将联伊援助团的任务期限延长了“最后19个月，直到2025年12月31日”，之后援助团“将停止工作和行动”。 美国常驻联合国副代表罗伯特·伍德说：“我们都认识到，伊拉克近年来发生了根本变化。有必要根据我们促进一个安全、稳定和拥有主权的伊拉克的承诺，重新调整联伊援助团。”他还说：“我们安理会成员将继续监测进展情况。” （参考消息）",
            "date_modified": "2024-06-01T12:46:28.000Z"
        },
        {
            "id": 3641070,
            "content_html": "",
            "title": "中国地震台网正式测定：06月01日20时37分在西藏那曲市尼玛县（北纬34.41度，东经86.45度）发生3.2级地震，震源深度10千米。",
            "date_modified": "2024-06-01T12:45:47.000Z"
        },
        {
            "id": 3641069,
            "content_html": "",
            "url": "https://finance.sina.cn/7x24/2024-06-01/detail-inaxfviv9469125.d.html",
            "title": "【6月15日起长三角铁路实施新列车运行图】从中国铁路上海局集团有限公司获悉，6月15日零时起，全国铁路将实施第三季度列车运行图。调图后，长三角铁路旅客列车开行总数达1325.5对，货运列车开行总数达1345.5对。新图进一步优化动车组列车开行结构，把长三角向稀缺方向增能、助力城际通勤、兼顾商务出行等作为重点，另外增开直通动车组列车5对；对长三角始发前往青岛、济南、荣成等多个稀缺方向作了运能补充。（央视新闻）",
            "date_modified": "2024-06-01T12:44:25.000Z"
        },
        {
            "id": 3641068,
            "content_html": "",
            "url": "https://finance.sina.cn/7x24/2024-06-01/detail-inaxfviu2692209.d.html",
            "title": "【2024六一档票房进入影史前三】据灯塔专业版，截至20时32分，2024年六一儿童节单日票房达1.84亿，超过2014年六一档单日票房，进入历史同档期前三位，仅次于2018、2019年六一档，《哆啦A梦：大雄的地球交响乐》《加菲猫家族》《末路狂花钱》位列单日票房前三位。",
            "date_modified": "2024-06-01T12:44:17.000Z"
        },
        {
            "id": 3641067,
            "content_html": "",
            "url": "https://finance.sina.cn/7x24/2024-06-01/detail-inaxfxmk7972662.d.html",
            "title": "【瑞士拟提高外国留学生学费至原来的三倍】日前，瑞士联邦议会国民院通过了一项提高外国留学生学费的提案，根据这项提案，外国留学生学费将至少提高至原来的三倍。瑞士国民院表示，瑞士大学收取的学费属于世界最低之列，而瑞士学生去国外知名高校留学，所付学费最高可达外国留学生在瑞士所缴学费的40倍。数据显示，瑞士大学入学率30年来几乎翻了一番，当前国际学生占入学总人数的三分之一。（央视财经）",
            "date_modified": "2024-06-01T12:41:37.000Z"
        },
        {
            "id": 3641066,
            "content_html": "",
            "url": "https://finance.sina.cn/7x24/2024-06-01/detail-inaxfxmk7972413.d.html",
            "title": "【乌拉圭首都发生枪击事件 致4死1伤】乌拉圭警方当地时间5月31日发布消息称，30日23时左右，乌拉圭首都蒙得维的亚马拉卡纳社区发生一起枪击事件，造成4人死亡，其中包括一名11岁的男孩，另有一名17岁未成年人受重伤。据悉，死者包括一名40岁的男子，以及他17岁的儿子；另外两名死者是这名40岁男子的侄子，年龄分别为18岁和11岁。根据警方的报告，这名40岁的男子有抢劫犯罪记录。目前案件还在调查中，警方尚未发布与犯罪嫌疑人有关的信息。（央视新闻）",
            "date_modified": "2024-06-01T12:39:15.000Z"
        },
        {
            "id": 3641065,
            "content_html": "",
            "url": "https://finance.sina.cn/7x24/2024-06-01/detail-inaxfviv9466874.d.html",
            "title": "【第四届中法跨境电商论坛在巴黎举办】第四届中法跨境电商论坛5月31日在巴黎举办，千余名中欧跨境电商业内人士在论坛上深入讨论跨境电商行业的问题与机遇，探索中欧跨境电商领域发展新方向。 法国前总理让-皮埃尔·拉法兰在视频致辞中表示，电商相关技术创新推动了全球经济发展，法中两国企业加强该领域合作至关重要。 论坛上，多家企业进行现场展示，其中一些企业为品牌提供直播带货服务。在研讨会、小组讨论等分会场，参展企业围绕跨境电商发展趋势、市场机遇等议题展开探讨和交流，共同探索应对新机遇与新挑战的策略。（新华社）",
            "date_modified": "2024-06-01T12:34:32.000Z"
        },
        {
            "id": 3641061,
            "content_html": "",
            "title": "【我国科学家研发出低功耗类脑芯片】据中国科学院自动化研究所消息，该所李国齐、徐波课题组与国内科技企业等单位合作，近日设计了一套能够实现动态计算的算法-软件-硬件协同设计的类脑神经形态SOC（System onChip）系统Speck，展示了类脑神经形态计算在融合高抽象层次大脑机制时的天然优势，相关研究在线发表于《自然·通讯》（Nature Communications）。该研究提出了“神经形态动态计算”的概念，通过设计了一种类脑神经形态系统Speck来实现基于注意力机制的动态计算，在硬件层面做到“没有输入，没有功耗”，在算法层面做到“有输入时，根据输入重要性程度动态调整计算”，从而在典型视觉场景任务功耗可低至0.7毫瓦，进一步挖掘了神经形态计算在性能和能效上的潜力。",
            "date_modified": "2024-06-01T12:22:38.000Z"
        },
        {
            "id": 3641060,
            "content_html": "",
            "url": "https://finance.sina.cn/7x24/2024-06-01/detail-inaxfviv9464244.d.html",
            "title": " 【第十届能源、资源、环境与可持续发展国际会议在江苏徐州举办】5月30日至31日，由中国矿业大学主办的第十届能源、资源、环境与可持续发展国际会议在江苏徐州举行，来自美国、英国、德国、加拿大、俄罗斯等20个国家和地区的350余名专家和代表参会。围绕大会主题“聚焦全球能源绿色低碳转型，推进产业升级和可持续发展”，与会代表共商能源领域转型方向与路径，共绘可持续发展蓝图，为推进全球能源绿色低碳转型和产业升级贡献思路。 （中新网）",
            "date_modified": "2024-06-01T12:22:26.000Z"
        },
        {
            "id": 3641059,
            "content_html": "",
            "url": "https://finance.sina.cn/7x24/2024-06-01/detail-inaxfviv9463388.d.html",
            "title": "【和胜股份取得首个产品碳足迹证书】 据和胜股份消息，5月31日，和胜股份动力电池托盘（FDS-HP19）获得了中国国家级认证机构中国质量认证中心颁发的基于ISO14067标准的产品碳足迹证书。此次产品碳足迹证书的获取标志着和胜股份在碳排放管理和量化方面迈出坚实有力的一步，为公司日后的碳减排工作奠定基础。",
            "date_modified": "2024-06-01T12:18:24.000Z"
        },
        {
            "id": 3641058,
            "content_html": "",
            "url": "https://finance.sina.cn/7x24/2024-06-01/detail-inaxfxmn4747086.d.html",
            "title": "【2024端午档预售票房破6000万】据猫眼专业版数据，截至6月1日20时，2024年端午档预售总票房突破6000万，《谈判专家》领跑端午档预售榜。",
            "date_modified": "2024-06-01T12:16:39.000Z"
        },
        {
            "id": 3641057,
            "content_html": "",
            "url": "https://finance.sina.cn/7x24/2024-06-01/detail-inaxfviv9462657.d.html",
            "title": "【南非执政党非洲人国民大会在议会选举中得票率第一】南非独立选举委员会6月1日发布的初步计票结果显示，执政党非洲人国民大会在国民议会（议会下院）选举中获得40.25%的选票，位列第一。（新华社）",
            "date_modified": "2024-06-01T12:14:41.000Z"
        },
        {
            "id": 3641056,
            "content_html": "",
            "url": "https://finance.sina.cn/7x24/2024-06-01/detail-inaxfxmn4746803.d.html",
            "title": "【商务部在长沙召开“投资中国”外国投资促进机构圆桌会】6月1日，商务部在长沙第十三届中部博览会期间召开“投资中国”外国投资促进机构圆桌会，商务部副部长兼国际贸易谈判副代表凌激主持，湖南省省委副书记李殿勋出席并致辞。来自加拿大、德国、日本、马来西亚、墨西哥、韩国、英国、美国等32个国家及地区的100余位投促机构、商协会、驻华使领馆及外资企业代表参会。凌激表示，中国政府坚定不移扩大对外开放，不断优化营商环境，切实保护外资企业合法权益。欢迎各国投资促进机构积极参与“投资中国”活动，让更多外国企业走进中国，投资中国。我们将大力支持外国投资促进机构在华发展投促业务，为投资中国作出积极贡献。（商务部）",
            "date_modified": "2024-06-01T12:14:04.000Z"
        },
        {
            "id": 3641055,
            "content_html": "",
            "url": "https://finance.sina.cn/7x24/2024-06-01/detail-inaxfviv9462206.d.html",
            "title": "【李斌：蔚来在算力方面“丧心病狂”，未来一两年内都是天花板】6月1日，2024（第二届）未来汽车先行者大会在深圳举行，蔚来创始人、董事长、CEO李斌表示，蔚来在算力布局方面一直“丧心病狂”，在未来一两年内都还会是全球天花板。",
            "date_modified": "2024-06-01T12:12:32.000Z"
        },
        {
            "id": 3641054,
            "content_html": "",
            "url": "https://finance.sina.cn/7x24/2024-06-01/detail-inaxfxmn4746516.d.html",
            "title": "【小鹏汇天：江门低空文旅小镇项目建设启动，预订100台飞行汽车】6月1日，小鹏汇天宣布，江门低空文旅小镇项目建设启动，预订100台“陆地航母”飞行汽车。据介绍，低空文旅小镇项目包括低空飞行体验、飞行汽车展示、飞行汽车养护、情景模拟互动、科普研学旅行、飞行人才培训、配套休闲娱乐服务设施。",
            "date_modified": "2024-06-01T12:11:04.000Z"
        },
        {
            "id": 3641053,
            "content_html": "",
            "url": "https://finance.sina.cn/7x24/2024-06-01/detail-inaxfxmk7969316.d.html",
            "title": "【美国、埃及和以色列官员将举行会议讨论重开拉法口岸】据埃及媒体6月1日报道，消息人士称，美国、埃及和以色列官员将于6月2日在埃及开罗举行会议，讨论重新开放拉法口岸的问题。5月30日曾有消息说，以色列和埃及同意重新开放加沙地带与埃及接壤的拉法口岸，以运送人道主义援助物资，双方将召开会议讨论具体方案。另据知情人士消息，以方已解除向加沙地带出售食品的禁令。（央视新闻）",
            "date_modified": "2024-06-01T12:10:25.000Z"
        },
        {
            "id": 3641049,
            "content_html": "",
            "url": "https://finance.sina.cn/7x24/2024-06-01/detail-inaxfviu2683533.d.html",
            "title": "市场消息：高盛考虑通过发放奖金以推动财富管理业务增长。",
            "date_modified": "2024-06-01T12:04:09.000Z"
        },
        {
            "id": 3641048,
            "content_html": "",
            "url": "https://finance.sina.cn/7x24/2024-06-01/detail-inaxfxmk7968216.d.html",
            "title": "【黎巴嫩真主党称在黎南部领空击落一架以军无人机】黎巴嫩真主党当地时间6月1日宣布在黎南部地区领空使用“适当的武器”击落一架以色列“赫尔墨斯”900型军用无人机。黎真主党声明并未提及事件发生的具体时间和地点。以色列方面对此暂无回应。",
            "date_modified": "2024-06-01T11:59:29.000Z"
        },
        {
            "id": 3641047,
            "content_html": "",
            "url": "https://finance.sina.cn/7x24/2024-06-01/detail-inaxfviv9459306.d.html",
            "title": "【中部地区现代石化产业链招商推介会签约204.4亿元】5月31日，第十三届中国中部投资贸易博览会中部地区现代石化产业链招商推介会由湖南牵头举办。来自中部六省的现代石化产业链重点企业客商代表、商协会、高校专家等各界人士汇聚一堂，深化中部地区产业对接合作，共话现代石化产业未来。推介会现场，170余名中外嘉宾和企业家代表齐聚一堂，现场成功签约项目18个，总投资额204.4亿元，其中10亿元以上项目6个，投资额164.3亿元；500强企业3个、上市企业3个、头部企业1个、高科技含量企业4个。",
            "date_modified": "2024-06-01T11:59:14.000Z"
        },
        {
            "id": 3641046,
            "content_html": "",
            "url": "https://finance.sina.cn/7x24/2024-06-01/detail-inaxfxmk7968127.d.html",
            "title": "【中部地区新能源产业链推介对接会签约额达235.8亿元】第十三届中部博览会期间，由山西省人民政府主办，山西省商务厅、山西省投资促进局承办的中部地区新能源产业链推介对接会5月31日在湖南长沙举行。对接会上，举行了重点项目签约，共签约23个重大项目，总投资额235.8亿元，主要涉及风电、光伏、氢能、新型储能、新能源汽车、节能环保、新材料、废弃资源综合利用等产业领域。项目成功签约，对推动山西新能源产业发展、深化区域投资合作起到积极促进作用。",
            "date_modified": "2024-06-01T11:58:45.000Z"
        },
        {
            "id": 3641045,
            "content_html": "",
            "url": "https://finance.sina.cn/7x24/2024-06-01/detail-inaxfviv9457688.d.html",
            "title": "【外媒：“封口费”案裁决公布后 特朗普团队筹得近5300万美元】据《纽约时报》5月31日报道，美国前总统特朗普在“封口费”案中被判有罪后，他的竞选团队在24小时内筹集到了近5300万美元。特朗普的竞选团队表示，裁决宣布后，他们在24小时内筹到了5280万美元，打破了共和党的网上筹款纪录，并缩小了特朗普和总统拜登之间的竞选资金差距。特朗普的高级顾问威尔斯和拉西维塔在一份联合声明中称，“这种势头才刚刚开始。”（中新网）",
            "date_modified": "2024-06-01T11:51:13.000Z"
        },
        {
            "id": 3641044,
            "content_html": "",
            "url": "https://finance.sina.cn/7x24/2024-06-01/detail-inaxfviv9457437.d.html",
            "title": "【国家能源集团与法国电力集团签署合作意向书】5月31日，国家能源集团与法国电力集团签署合作意向书。国家能源集团董事、总经理余兵和法国电力集团董事长兼首席执行官雷蒙进行会谈，并见证双方签约。国家能源集团副总经理徐新福，法国电力集团副总裁兼中国区总裁傅楷德代表双方签约。",
            "date_modified": "2024-06-01T11:50:13.000Z"
        },
        {
            "id": 3641043,
            "content_html": "",
            "title": "【吉尔吉斯斯坦逮捕6名极端组织成员】吉尔吉斯斯坦国家安全委员会新闻局6月1日通报，宗教极端组织“伊斯兰解放党”的6名成员日前在吉南部被捕。通报说，这6名“伊斯兰解放党”成员频频宣传极端主义思想，已于5月31日在贾拉拉巴德州的苏扎克地区被捕。吉强力部门同时没收其大量宣扬极端主义思想的传单和存有极端主义性质文件的手机等电子设备。通报说，为了招募更多追随者，这6人在当地民众中系统性地宣传极端主义思想。（央视新闻）",
            "date_modified": "2024-06-01T11:47:39.000Z"
        },
        {
            "id": 3641042,
            "content_html": "",
            "url": "https://finance.sina.cn/7x24/2024-06-01/detail-inaxfviu2679636.d.html",
            "title": "【印度：创纪录的52.9℃有3℃的误差】印度政府周六表示，创纪录的52.9℃有3℃的误差，原因是传感器故障。印度地球科学部长Kiren Rijiju表示，印度气象部门(IMD)调查了首都人口稠密的Mungeshpur气象站周三的读数，发现了3°C的传感器误差。（环球市场播报）",
            "date_modified": "2024-06-01T11:46:01.000Z"
        },
        {
            "id": 3641041,
            "content_html": "",
            "url": "https://finance.sina.cn/7x24/2024-06-01/detail-inaxfviu2679015.d.html",
            "title": "南非经济自由斗士党领袖朱利叶斯·马莱马：我们将与所有政党接触，以便组建政府。",
            "date_modified": "2024-06-01T11:42:50.000Z"
        },
        {
            "id": 3641040,
            "content_html": "",
            "url": "https://finance.sina.cn/7x24/2024-06-01/detail-inaxfviv9455159.d.html",
            "title": "【深圳市市委书记孟凡利与蔚来汽车李斌一行会谈】孟凡利欢迎蔚来汽车进一步加大在深投资和业务布局，不断深化双方在各有关领域务实合作，实现互利共赢、共同发展，携手共创美好未来。我们将持续营造更加完备、更富吸引力、更具性价比的产业生态，全力做好服务保障，支持企业在深实现更好更快更大发展。李斌介绍了企业经营和在深发展情况，表示深圳在改革开放、创新发展上始终勇立潮头，蔚来汽车将深耕粤港澳大湾区和深圳市场，加强交流对接，充分挖掘各相关领域潜在机遇，深化务实合作，为深圳高质量发展贡献力量。（深圳发布）",
            "date_modified": "2024-06-01T11:39:39.000Z"
        },
        {
            "id": 3641039,
            "content_html": "",
            "url": "https://finance.sina.cn/7x24/2024-06-01/detail-inaxfviv9454668.d.html",
            "title": "【2024年观影人次破5亿】据猫眼专业版数据，截至6月1日19时29分，2024年总观影人次突破5亿，全年总票房218.57亿，总场次6024.9万。《热辣滚烫》《飞驰人生2》《第二十条》分列2024年观影人次榜前三位。",
            "date_modified": "2024-06-01T11:37:51.000Z"
        },
        {
            "id": 3641038,
            "content_html": "",
            "url": "https://finance.sina.cn/7x24/2024-06-01/detail-inaxfxmk7965794.d.html",
            "title": "【朝鲜超大型火箭炮兵部队示威射击】据朝中社5月31日报道，朝鲜劳动党总书记、国务委员长金正恩指导朝鲜超大型火箭炮兵部队进行示威射击，击中了365公里外的目标岛屿。同一天，韩国统一部警告称，若朝方继续发起挑衅，韩方将采取朝方难以承受的措施进行回应。（央视军事）",
            "date_modified": "2024-06-01T11:35:42.000Z"
        },
        {
            "id": 3641037,
            "content_html": "",
            "url": "https://finance.sina.cn/7x24/2024-06-01/detail-inaxfviv9453610.d.html",
            "title": "【捷捷微电与晶能（吉利旗下子公司）签署深化合作战略协议】 据捷捷微电消息，江苏捷捷微电子股份有限公司（简称“捷捷微电”）与总部位于杭州的浙江晶能微电子有限公司（简称“晶能”，吉利旗下子公司）合作，并战略合作协议。双方将进一步加强在工控IGBT领域的战略合作，并拓展在汽车电子领域的合作范围。晶能是吉利科技旗下的功率半导体公司。",
            "date_modified": "2024-06-01T11:33:30.000Z"
        },
        {
            "id": 3641036,
            "content_html": "",
            "url": "https://finance.sina.cn/7x24/2024-06-01/detail-inaxfviu2676385.d.html",
            "title": "【莫万贵：发展和规范并重 促进数字金融行稳致远】6月1日下午，第十三届中国中部投资贸易博览会主题活动“产业数字金融合作对接会”在湖南省长沙市举办。中国人民银行金融研究所副所长莫万贵在主旨演讲中介绍，中国人民银行正积极推动数字金融加快发展，要发展和规范并重，促进数字金融守正创新、行稳致远。莫万贵主要介绍了四方面内容。首先，规范智能算法金融应用；其次，还要重视数字鸿沟问题，践行数字普惠金融；第三，重视监管科技应用，增强数字化监管能力；最后，坚持服务实体经济和守正创新，发挥好抑制“伪创新”和保护“真创新”的作用，在防范和化解潜在金融风险的同时促进数字金融服务实体经济有序健康发展。（上证报）",
            "date_modified": "2024-06-01T11:31:42.000Z"
        },
        {
            "id": 3641034,
            "content_html": "",
            "url": "https://finance.sina.cn/7x24/2024-06-01/detail-inaxfviu2675094.d.html",
            "title": "达美航空首席执行官：对波音公司新任董事长的变化感到鼓舞。",
            "date_modified": "2024-06-01T11:25:28.000Z"
        },
        {
            "id": 3641033,
            "content_html": "",
            "url": "https://finance.sina.cn/7x24/2024-06-01/detail-inaxfviu2674899.d.html",
            "title": "【浙江小麦最高百亩方亩产新纪录诞生】 6月1日，浙江省农业农村厅发布消息，浙江农业之最小麦最高百亩方亩产新纪录日前诞生，达到551.16公斤/亩。此前，浙江农业之最委员会办公室组织相关专家，对该省平湖市钟埭街道得稻家庭农场有限公司张良杰申报的120亩小麦进行测产验收。根据验收方法，专家组经现场查看后，选取三块1亩以上田块，采用收割机全田实割测产，折算成标准水分和净度后，测得百亩方平均亩产551.16公斤，打破2022年由张良杰自己创造的542.25公斤/亩的浙江农业之最纪录。（中新网）",
            "date_modified": "2024-06-01T11:24:13.000Z"
        },
        {
            "id": 3641032,
            "content_html": "",
            "url": "https://finance.sina.cn/7x24/2024-06-01/detail-inaxfviv9451466.d.html",
            "title": "美国-埃及-以色列定于周日在开罗举行会议，与加沙讨论重新开放拉法过境点的问题。",
            "date_modified": "2024-06-01T11:22:24.000Z"
        },
        {
            "id": 3641031,
            "content_html": "",
            "url": "https://finance.sina.cn/7x24/2024-06-01/detail-inaxfviv9450626.d.html",
            "title": "【格鲁吉亚总理：美国资助的NGO试图推翻格政府 将重新审视对美关系】综合路透社和今日俄罗斯电视台网站5月31日报道，格鲁吉亚总理伊拉克利·科巴希泽呼吁重新审视该国与美国的关系。此前，华盛顿下令针对格鲁吉亚通过一项有关“外国代理人”的法律采取惩罚措施。 科巴希泽5月31日表示，考虑到美国资助的非政府组织（NGO）策动了至少两次试图推翻格鲁吉亚政府的图谋，第比利斯需要“审视”其与华盛顿的关系。 科巴希泽说：“我不知道这些人为什么会有发动革命的图谋，一次是在2020年至2021年，另一次是在2022年。我不知道为什么会有这些图谋，但事实是前任（美国）大使破坏了很多事情……这些需要得到纠正。” 他还说：“这些事情涉及美国资助的非政府组织，它们……要求政府辞职，然后组建有它们参与的政府。因此，格鲁吉亚与美国的关系的确必须加以审视。” （参考消息）",
            "date_modified": "2024-06-01T11:18:16.000Z"
        },
        {
            "id": 3641030,
            "content_html": "",
            "url": "https://finance.sina.cn/7x24/2024-06-01/detail-inaxfviu2673293.d.html",
            "title": "【阿富汗东部沉船事故已致8人死亡5人失踪】阿富汗官员当地时间6月1日称，阿东部楠格哈尔省当天发生船只倾覆事故，造成至少8人死亡、5人失踪。楠格哈尔省信息和文化部门负责人库雷希·巴德伦表示，事故当天上午发生在该省穆曼德达拉区的一条河流中。涉事船只载有26名乘客，大多为妇女和儿童，其中13人已获救。巴德伦说，搜救人员仍在现场进行救援，事故具体原因还有待调查。（央视新闻）",
            "date_modified": "2024-06-01T11:15:54.000Z"
        },
        {
            "id": 3641029,
            "content_html": "",
            "url": "https://finance.sina.cn/7x24/2024-06-01/detail-inaxfviu2673150.d.html",
            "title": "【俄称击落乌无人机 乌称能源设施遭袭】俄罗斯国防部称，6月1日俄军防空系统在别尔哥罗德州击落了2架乌克兰无人机。6月1日，乌克兰能源部长发布消息称，当天凌晨俄军袭击了扎波罗热、第聂伯罗彼得罗夫斯克等地的能源设施。另据乌克兰军方发布的消息，乌克兰防空系统当天拦截了46架俄方无人机和35枚俄方导弹。",
            "date_modified": "2024-06-01T11:15:24.000Z"
        },
        {
            "id": 3641028,
            "content_html": "",
            "url": "https://finance.sina.cn/7x24/2024-06-01/detail-inaxfxmn4741008.d.html",
            "title": "【智利北部地区发生5.5级地震】根据欧洲-地中海地震中心报告，当地时间6月1日6时53分，智利北部安托法加斯塔大区发生5.5级地震，震源深度118公里。目前暂无人员伤亡及财产损失报告，同时已排除海啸警报。",
            "date_modified": "2024-06-01T11:14:07.000Z"
        },
        {
            "id": 3641027,
            "content_html": "",
            "url": "https://finance.sina.cn/7x24/2024-06-01/detail-inaxfxmn4740976.d.html",
            "title": "印度表示，创纪录的52.9摄氏度气温错了3摄氏度。",
            "date_modified": "2024-06-01T11:13:50.000Z"
        },
        {
            "id": 3641026,
            "content_html": "",
            "url": "https://finance.sina.cn/7x24/2024-06-01/detail-inaxfviu2672595.d.html",
            "title": "【东风风行星海V9车型正式上市】6月1日，东风风行星海V9上市发布会暨首批车主交车仪式在广州举行。风行星海V9全球正式上市，售价为19.99万元-27.99万元。",
            "date_modified": "2024-06-01T11:13:17.000Z"
        },
        {
            "id": 3641024,
            "content_html": "",
            "url": "https://finance.sina.cn/7x24/2024-06-01/detail-inaxfxmk7963513.d.html",
            "title": "【哪吒汽车：5月全系整车交付10,113台】6月1日，哪吒汽车宣布，5月全系整车交付10,113台。",
            "date_modified": "2024-06-01T11:10:48.000Z"
        },
        {
            "id": 3641023,
            "content_html": "",
            "url": "https://finance.sina.cn/7x24/2024-06-01/detail-inaxfxmk7963496.d.html",
            "title": "【中部地区电子信息产业链招商推介会签约38个项目】 5月31日，以第十三届中国中部投资贸易博览会举办为契机，江西牵头举办中部地区电子信息产业链招商推介会，大力推介重点项目和支持政策，共同探讨合作与发展的机遇。现场签约电子信息产业项目38个。据介绍，2024年前四个月江西全省投资亿元以上电子信息产业链项目达781个，电子信息产业基本形成了大中小企业梯度培育、融通发展格局。（中证报）",
            "date_modified": "2024-06-01T11:10:36.000Z"
        },
        {
            "id": 3641022,
            "content_html": "",
            "url": "https://finance.sina.cn/7x24/2024-06-01/detail-inaxfviu2671688.d.html",
            "title": "【深圳市市委书记孟凡利与小米集团雷军一行会谈】孟凡利说，我们愿与小米集团进一步加大合作力度，支持企业在深业务取得更好发展，积极争取在各领域取得更多互利共赢成果。我们将全力打造一流营商环境，强化各类要素保障，为企业提供优质高效的服务。雷军介绍了小米集团经营和在深发展情况，表示深圳是一座年轻、创新、充满活力的城市，是小米集团业务发展的重要区域和重要市场。小米集团将充分发挥自身科技创新和生态整合优势，积极加强各相关领域务实合作，实现共赢发展。",
            "date_modified": "2024-06-01T11:10:20.000Z"
        },
        {
            "id": 3641021,
            "content_html": "",
            "url": "https://finance.sina.cn/7x24/2024-06-01/detail-inaxfviv9448170.d.html",
            "title": "【潘多拉改用培育钻石销售额暴增】近年来，随着年轻群体消费观念的转变，质优价美的培育钻石人气大涨，甚至有赶超天然钻石之势。数据显示，今年4月份，培育钻石在美国市场份额达56.8%，国际珠宝行业也掀起了一波培育钻石销售热潮。丹麦珠宝品牌潘多拉，2021年宣布不再使用天然钻石，全面进军人工培育钻。潘多拉财报显示，第一季度其培育钻石销售额同比激增87%，达到6300万丹麦克朗（约合人民币6600万元）。",
            "date_modified": "2024-06-01T11:08:28.000Z"
        },
        {
            "id": 3641020,
            "content_html": "",
            "url": "https://finance.sina.cn/7x24/2024-06-01/detail-inaxfviu2671239.d.html",
            "title": "【乌克兰多地能源设施遭大规模空袭】乌克兰国家电力公司6月1日在社交媒体发文说，当天凌晨，俄军对乌境内能源设施发动大规模空袭。袭击导致扎波罗热州、第聂伯罗彼得罗夫斯克州、基洛沃格勒州、伊万诺-弗兰科夫斯克州和顿涅茨克地区的能源设施受损。乌国家电力公司5月28日表示，俄军此前的袭击已导致该国损失近40%的电力产能。 乌克兰最大的私营能源企业顿巴斯燃料和能源公司说，该公司旗下两座火力发电厂在6月1日的空袭中严重受损。在过去数月的俄军袭击中，该公司有3名员工死亡、51名员工受伤。 俄国防部同日在社交媒体上说，为回应乌方破坏俄能源和交通设施的企图，俄军使用高精度远程空基和海基武器，已对乌方保障军工企业运转的能源设施实施了集群打击。（新华社）",
            "date_modified": "2024-06-01T11:08:12.000Z"
        },
        {
            "id": 3641018,
            "content_html": "",
            "title": "中国地震台网正式测定：06月01日18时58分在西藏那曲市尼玛县（北纬34.23度，东经86.33度）发生3.7级地震，震源深度10千米。",
            "date_modified": "2024-06-01T11:07:11.000Z"
        },
        {
            "id": 3641015,
            "content_html": "",
            "url": "https://finance.sina.cn/7x24/2024-06-01/detail-inaxfqzw2800343.d.html",
            "title": "以色列军方称，其一架无人机在黎巴嫩领土上被地对空导弹击落。",
            "date_modified": "2024-06-01T11:01:42.000Z"
        },
        {
            "id": 3641014,
            "content_html": "",
            "url": "https://finance.sina.cn/7x24/2024-06-01/detail-inaxfqzw2800034.d.html",
            "title": "【责令停产停业85家 多部门联手开展校园食品安全排查整治】记者今天（6月1日）从市场监管总局了解到。从2023年12月起，在国务院食安办指导下，市场监管总局联合教育部、公安部、国家卫生健康委等部门开展校园食品安全排查整治专项行动，聚焦校园食品安全问题的痛点、难点、堵点。截至目前，专项行动开展以来发现并整改问题48.5万个，立案查处违法案件1.02万件，责令停产停业85家，吊销许可证6家，取缔无证经营14家，列入严重违法失信名单2家，校园食品安全形势得到稳步提升。（央视新闻）",
            "date_modified": "2024-06-01T11:00:37.000Z"
        },
        {
            "id": 3641013,
            "content_html": "",
            "url": "https://finance.sina.cn/7x24/2024-06-01/detail-inaxfqzx9575929.d.html",
            "title": "【新款捷尼赛思G80正式上市，29.98万起售】6月1日，捷尼赛思登陆2024粤港澳大湾区车展，宣布新款捷尼赛思G80正式上市，起售价29.98万元。",
            "date_modified": "2024-06-01T10:56:19.000Z"
        },
        {
            "id": 3641010,
            "content_html": "",
            "url": "https://finance.sina.cn/7x24/2024-06-01/detail-inaxftcn8092360.d.html",
            "title": "【河北曲阳县通报一起刑事案件：一人持刀致3人受伤，伤者经抢救无效死亡】6月1日，河北保定市曲阳县公安局发布警情通报：2024年5月31日11时许，曲阳县燕赵镇寺留营村发生一起刑事案件，犯罪嫌疑人窦某某被警方当场抓获，已被依法刑事拘留。经查，窦某某与马某某因经济纠纷在电话中互相辱骂对方，后在本村街上相遇，窦某某持刀致马某某等3人受伤，伤者被紧急送医，经抢救无效死亡。目前，案件正在进一步侦办中。",
            "date_modified": "2024-06-01T10:53:31.000Z"
        },
        {
            "id": 3641009,
            "content_html": "",
            "url": "https://finance.sina.cn/7x24/2024-06-01/detail-inaxftcn8092322.d.html",
            "title": "【外媒：泽连斯基抵达新加坡，将参加香格里拉对话会】据法新社6月1日报道，乌克兰总统泽连斯基抵达新加坡，他将参加香格里拉对话会。 报道称，法新社记者看到，泽连斯基走进了举办香格里拉对话会的酒店。 另据新加坡《海峡时报》6月1日报道，乌克兰总统泽连斯基已抵达新加坡，将在明天香格里拉对话会（简称“香会”）活动上发表演讲，该媒体还发布了泽连斯基抵达后的现场视频。 综合新加坡《联合早报》、路透社5月31日报道，泽连斯基将参加在新加坡举行的香格里拉对话会并发表演讲。 （环球网）",
            "date_modified": "2024-06-01T10:53:12.000Z"
        },
        {
            "id": 3641007,
            "content_html": "",
            "title": "以色列主要反对党领导人、前总理拉皮德：不要忽视拜登在加沙的讲话，谈判桌上必须达成协议。如果内塔尼亚胡的极右翼伙伴退出，以色列反对派将在人质交易上支持内塔尼亚胡。",
            "date_modified": "2024-06-01T10:42:02.000Z"
        }
    ]
}